easySocket/__init__.py
easySocket-0.0.3.dist-info/LICENSE
easySocket-0.0.3.dist-info/METADATA
easySocket-0.0.3.dist-info/WHEEL
easySocket-0.0.3.dist-info/top_level.txt
easySocket-0.0.3.dist-info/RECORD
