Metadata-Version: 2.1
Name: easySocket
Version: 0.0.3
Summary: A tool, based on socket, to make sending big files(like images) easier/simpler.
Home-page: https://github.com/N-Ziermann/easySocket
Author: N-Ziermann
Author-email: N-Ziermann@protonmail.com
License: UNKNOWN
Platform: UNKNOWN
Classifier: Programming Language :: Python :: 3
Classifier: License :: OSI Approved :: MIT License
Classifier: Operating System :: OS Independent
